README
setup.cfg
setup.py
itelsupply/__init__.py
itelsupply/core.py
itelsupply.egg-info/PKG-INFO
itelsupply.egg-info/SOURCES.txt
itelsupply.egg-info/dependency_links.txt
itelsupply.egg-info/requires.txt
itelsupply.egg-info/top_level.txt