Metadata-Version: 1.1
Name: itelsupply
Version: 0.2
Summary: Python API client for 
Home-page: https://github.com/makmac213/
Author: Mark Allan B Meriales
Author-email: mark.meriales@gmail.com
License: UNKNOWN
Download-URL: https://github.com/makmac213/python-itelsupply
Platform: UNKNOWN
Classifier: Development Status :: 4 - Beta
Classifier: Intended Audience :: Developers
Classifier: Natural Language :: English
Classifier: Programming Language :: Python
Classifier: License :: Freeware
